wagtailmath/__init__.py
wagtailmath/apps.py
wagtailmath/blocks.py
wagtailmath/models.py
wagtailmath/widgets.py
wagtailmath/static/wagtailmath/js/mathjax-textarea-adapter.js
wagtailmath/static/wagtailmath/js/wagtailmath-mathjax-controller.js
wagtailmath/static/wagtailmath/js/wagtailmath.js
wagtailmath/templates/wagtailmath/mathjaxwidget.html
wagtailmath/templatetags/__init__.py
wagtailmath/templatetags/wagtailmath.py
wagtailmath-1.3.1.dist-info/LICENSE
wagtailmath-1.3.1.dist-info/WHEEL
wagtailmath-1.3.1.dist-info/METADATA
wagtailmath-1.3.1.dist-info/RECORD
