Metadata-Version: 2.1
Name: wagtailmath
Version: 1.3.1
Summary: Wagtail StreamField block for rendering mathematical equations
Author-email: James Ramm <jamessramm@gmail.com>
Requires-Python: >=3.8
Classifier: Development Status :: 3 - Alpha
Classifier: Intended Audience :: Developers
Classifier: License :: OSI Approved :: BSD License
Classifier: Operating System :: OS Independent
Classifier: Programming Language :: Python
Classifier: Programming Language :: Python :: 3
Classifier: Programming Language :: Python :: 3.8
Classifier: Programming Language :: Python :: 3.9
Classifier: Programming Language :: Python :: 3.10
Classifier: Programming Language :: Python :: 3.11
Classifier: Programming Language :: Python :: 3.12
Classifier: Framework :: Django
Classifier: Framework :: Django :: 4.2
Classifier: Framework :: Django :: 5.0
Classifier: Framework :: Wagtail
Classifier: Framework :: Wagtail :: 5
Classifier: Framework :: Wagtail :: 6
Requires-Dist: Django>=4.2
Requires-Dist: Wagtail>=5.2
Requires-Dist: tox>=4.15.1,<5 ; extra == "ci"
Requires-Dist: tox-gh-actions>=3.2,<3.3 ; extra == "ci"
Requires-Dist: pre-commit>=3.6.0,<4 ; extra == "linting"
Requires-Dist: dj-database-url==2.1.0 ; extra == "testing"
Requires-Dist: pytest==8.1.1 ; extra == "testing"
Requires-Dist: pytest-cov==5.0.0 ; extra == "testing"
Requires-Dist: pytest-django==4.8.0 ; extra == "testing"
Project-URL: Changelog, https://github.com/wagtail-nest/wagtail-polymath/blob/main/CHANGELOG.md
Project-URL: Documentation, https://github.com/wagtail-nest/wagtail-polymath/blob/main/docs/
Project-URL: Home, https://github.com/wagtail-nest/wagtail-polymath
Provides-Extra: ci
Provides-Extra: linting
Provides-Extra: testing
